smlmain/__init__.py
smlmain/main_sml.py
smlmain-0.1.dist-info/METADATA
smlmain-0.1.dist-info/WHEEL
smlmain-0.1.dist-info/top_level.txt
smlmain-0.1.dist-info/RECORD
