Metadata-Version: 2.1
Name: smlmain
Version: 0.1
Summary: A description of your package
Home-page: https://github.com/priyanshi58/smlmain
Author: Priyanshi Mehta
Author-email: dhwanimehta2003@gmail.com
Classifier: Programming Language :: Python :: 3
Classifier: License :: OSI Approved :: MIT License
